{
	"configurations" : 
	[
		{
			"directories" : 
			[
				{
					"build" : ".",
					"minimumCMakeVersion" : 
					{
						"string" : "3.15"
					},
					"projectIndex" : 0,
					"source" : ".",
					"targetIndexes" : 
					[
						0
					]
				}
			],
			"name" : "Debug",
			"projects" : 
			[
				{
					"directoryIndexes" : 
					[
						0
					],
					"name" : "particle_velocity",
					"targetIndexes" : 
					[
						0
					]
				}
			],
			"targets" : 
			[
				{
					"directoryIndex" : 0,
					"id" : "particle_velocity::@6890427a1f51a3e7e1df",
					"jsonFile" : "target-particle_velocity-Debug-c6f1ed6b03745230cb4b.json",
					"name" : "particle_velocity",
					"projectIndex" : 0
				}
			]
		}
	],
	"kind" : "codemodel",
	"paths" : 
	{
		"build" : "C:/Users/Abhishek.Sharma1/source/repos/Abhisharma499/Data-Structure/Microsoft/particle_velocity/out/build/x64-Debug",
		"source" : "C:/Users/Abhishek.Sharma1/source/repos/Abhisharma499/Data-Structure/Microsoft/particle_velocity"
	},
	"version" : 
	{
		"major" : 2,
		"minor" : 2
	}
}
